jarvis_dicom/__init__.py
jarvis_dicom/main.py
jarvis_dicom/parser.py
jarvis_dicom/reader.py
jarvis_md_dicom-0.0.1a1.dist-info/METADATA
jarvis_md_dicom-0.0.1a1.dist-info/WHEEL
jarvis_md_dicom-0.0.1a1.dist-info/entry_points.txt
jarvis_md_dicom-0.0.1a1.dist-info/top_level.txt
jarvis_md_dicom-0.0.1a1.dist-info/RECORD
